Workbook

Sheet Read me
B2: SmartBiz Estate: end-to-end process test script (Sprints 0-10)
B3: Walks a landlord, an agency and a developer through the whole system in business order, so later steps build on earlier ones.
B5: Before you start
B6: 1. Fresh database | C6: Demo dates are relative to the day the data is seeded. Start from a clean database so expected values match: dotnet ef database drop --force --project src/RealEstateERP.Infrastructure --startup-project src/RealEstateERP.Web
B7: 2. Run in Development | C7: dotnet run --project src/RealEstateERP.Web Migrations are applied and demo data is seeded on first start.
B8: 3. Email | C8: Without SMTP, every email lands in the dev mailbox at /dev/mailbox. With SMTP (Admin > Settings > Email), use addresses you can open.
B9: 4. Order | C9: Run the steps top to bottom. Development costing (S9b) comes before Sales (S9) so its demo numbers hold.
B10: 5. Credits | C10: Some steps use credits (PDFs, leads, invoice runs). If a business runs low, top it up via superadmin (Admin > Credit purchases > adjust).
B12: Demo accounts (password for all: Demo@12345)
B13: superadmin@smartbiz.test | C13: Platform admin: payment approvals, plans, settings, users, businesses
B14: owner@smartbiz.test | C14: Owns Acacia Gardens (landlord) and Savanna Homes (developer, plot sales)
B15: admin@smartbiz.test | C15: Admin at Acacia Gardens
B16: staff@smartbiz.test | C16: User at Acacia Gardens (can edit, can't renew or manage team)
B17: viewer@smartbiz.test | C17: Viewer at Acacia Gardens (read-only)
B18: agent@smartbiz.test | C18: Principal of Mji Property Agents (agency)
B19: james@smartbiz.test | C19: Agent at Mji Property Agents: sees only his own contracts and sales
B20: lapsed@smartbiz.test | C20: Owns Lapsed Holdings: suspended, payment awaiting approval
B21: newuser@smartbiz.test | C21: No business yet
B23: How to record results
B24: Cells you fill in | C24: Only the shaded columns on 'Test script': Status, Actual result / notes, Tester, Date. Everything else is the script.
B25: Status | C25: Pick from the list: Not run, Pass, Fail, Blocked. 'Blocked' = couldn't run because an earlier step failed.
B26: Fail | C26: Write what actually happened in 'Actual result / notes', then log it on 'Defects' with the test ID. The example row there shows the format.
B27: Summary | C27: Counts and pass rate per sprint update automatically from the Status column.

Sheet Summary
B2: Results by sprint
B3: Updates automatically from the Status column on 'Test script'. Pass rate = Pass / (steps run).
B5: Sprint | C5: Steps | D5: Pass | E5: Fail | F5: Blocked | G5: Not run | H5: Run | I5: Pass rate
B6: S0 Foundation | C6: =COUNTIF('Test script'!$B$2:$B$133,B6) -> 11 | D6: =COUNTIFS('Test script'!$B$2:$B$133,$B6,'Test script'!$H$2:$H$133,"Pass") -> 0 | E6: =COUNTIFS('Test script'!$B$2:$B$133,$B6,'Test script'!$H$2:$H$133,"Fail") -> 0 | F6: =COUNTIFS('Test script'!$B$2:$B$133,$B6,'Test script'!$H$2:$H$133,"Blocked") -> 0 | G6: =COUNTIFS('Test script'!$B$2:$B$133,$B6,'Test script'!$H$2:$H$133,"Not run") -> 11 | H6: =C6-G6 -> 0 | I6: =IF(H6=0,"-",D6/H6) -> -
B7: S1 Subscriptions | C7: =COUNTIF('Test script'!$B$2:$B$133,B7) -> 8 | D7: =COUNTIFS('Test script'!$B$2:$B$133,$B7,'Test script'!$H$2:$H$133,"Pass") -> 0 | E7: =COUNTIFS('Test script'!$B$2:$B$133,$B7,'Test script'!$H$2:$H$133,"Fail") -> 0 | F7: =COUNTIFS('Test script'!$B$2:$B$133,$B7,'Test script'!$H$2:$H$133,"Blocked") -> 0 | G7: =COUNTIFS('Test script'!$B$2:$B$133,$B7,'Test script'!$H$2:$H$133,"Not run") -> 8 | H7: =C7-G7 -> 0 | I7: =IF(H7=0,"-",D7/H7) -> -
B8: S2 Portfolio | C8: =COUNTIF('Test script'!$B$2:$B$133,B8) -> 7 | D8: =COUNTIFS('Test script'!$B$2:$B$133,$B8,'Test script'!$H$2:$H$133,"Pass") -> 0 | E8: =COUNTIFS('Test script'!$B$2:$B$133,$B8,'Test script'!$H$2:$H$133,"Fail") -> 0 | F8: =COUNTIFS('Test script'!$B$2:$B$133,$B8,'Test script'!$H$2:$H$133,"Blocked") -> 0 | G8: =COUNTIFS('Test script'!$B$2:$B$133,$B8,'Test script'!$H$2:$H$133,"Not run") -> 7 | H8: =C8-G8 -> 0 | I8: =IF(H8=0,"-",D8/H8) -> -
B9: S3 Tenants and leases | C9: =COUNTIF('Test script'!$B$2:$B$133,B9) -> 9 | D9: =COUNTIFS('Test script'!$B$2:$B$133,$B9,'Test script'!$H$2:$H$133,"Pass") -> 0 | E9: =COUNTIFS('Test script'!$B$2:$B$133,$B9,'Test script'!$H$2:$H$133,"Fail") -> 0 | F9: =COUNTIFS('Test script'!$B$2:$B$133,$B9,'Test script'!$H$2:$H$133,"Blocked") -> 0 | G9: =COUNTIFS('Test script'!$B$2:$B$133,$B9,'Test script'!$H$2:$H$133,"Not run") -> 9 | H9: =C9-G9 -> 0 | I9: =IF(H9=0,"-",D9/H9) -> -
B10: S4 Billing | C10: =COUNTIF('Test script'!$B$2:$B$133,B10) -> 8 | D10: =COUNTIFS('Test script'!$B$2:$B$133,$B10,'Test script'!$H$2:$H$133,"Pass") -> 0 | E10: =COUNTIFS('Test script'!$B$2:$B$133,$B10,'Test script'!$H$2:$H$133,"Fail") -> 0 | F10: =COUNTIFS('Test script'!$B$2:$B$133,$B10,'Test script'!$H$2:$H$133,"Blocked") -> 0 | G10: =COUNTIFS('Test script'!$B$2:$B$133,$B10,'Test script'!$H$2:$H$133,"Not run") -> 8 | H10: =C10-G10 -> 0 | I10: =IF(H10=0,"-",D10/H10) -> -
B11: S5 Collections | C11: =COUNTIF('Test script'!$B$2:$B$133,B11) -> 9 | D11: =COUNTIFS('Test script'!$B$2:$B$133,$B11,'Test script'!$H$2:$H$133,"Pass") -> 0 | E11: =COUNTIFS('Test script'!$B$2:$B$133,$B11,'Test script'!$H$2:$H$133,"Fail") -> 0 | F11: =COUNTIFS('Test script'!$B$2:$B$133,$B11,'Test script'!$H$2:$H$133,"Blocked") -> 0 | G11: =COUNTIFS('Test script'!$B$2:$B$133,$B11,'Test script'!$H$2:$H$133,"Not run") -> 9 | H11: =C11-G11 -> 0 | I11: =IF(H11=0,"-",D11/H11) -> -
B12: S6 Arrears, credits, PDFs | C12: =COUNTIF('Test script'!$B$2:$B$133,B12) -> 8 | D12: =COUNTIFS('Test script'!$B$2:$B$133,$B12,'Test script'!$H$2:$H$133,"Pass") -> 0 | E12: =COUNTIFS('Test script'!$B$2:$B$133,$B12,'Test script'!$H$2:$H$133,"Fail") -> 0 | F12: =COUNTIFS('Test script'!$B$2:$B$133,$B12,'Test script'!$H$2:$H$133,"Blocked") -> 0 | G12: =COUNTIFS('Test script'!$B$2:$B$133,$B12,'Test script'!$H$2:$H$133,"Not run") -> 8 | H12: =C12-G12 -> 0 | I12: =IF(H12=0,"-",D12/H12) -> -
B13: S7 Accounts and admin | C13: =COUNTIF('Test script'!$B$2:$B$133,B13) -> 16 | D13: =COUNTIFS('Test script'!$B$2:$B$133,$B13,'Test script'!$H$2:$H$133,"Pass") -> 0 | E13: =COUNTIFS('Test script'!$B$2:$B$133,$B13,'Test script'!$H$2:$H$133,"Fail") -> 0 | F13: =COUNTIFS('Test script'!$B$2:$B$133,$B13,'Test script'!$H$2:$H$133,"Blocked") -> 0 | G13: =COUNTIFS('Test script'!$B$2:$B$133,$B13,'Test script'!$H$2:$H$133,"Not run") -> 16 | H13: =C13-G13 -> 0 | I13: =IF(H13=0,"-",D13/H13) -> -
B14: S8 Agency | C14: =COUNTIF('Test script'!$B$2:$B$133,B14) -> 14 | D14: =COUNTIFS('Test script'!$B$2:$B$133,$B14,'Test script'!$H$2:$H$133,"Pass") -> 0 | E14: =COUNTIFS('Test script'!$B$2:$B$133,$B14,'Test script'!$H$2:$H$133,"Fail") -> 0 | F14: =COUNTIFS('Test script'!$B$2:$B$133,$B14,'Test script'!$H$2:$H$133,"Blocked") -> 0 | G14: =COUNTIFS('Test script'!$B$2:$B$133,$B14,'Test script'!$H$2:$H$133,"Not run") -> 14 | H14: =C14-G14 -> 0 | I14: =IF(H14=0,"-",D14/H14) -> -
B15: S9b Development costing | C15: =COUNTIF('Test script'!$B$2:$B$133,B15) -> 10 | D15: =COUNTIFS('Test script'!$B$2:$B$133,$B15,'Test script'!$H$2:$H$133,"Pass") -> 0 | E15: =COUNTIFS('Test script'!$B$2:$B$133,$B15,'Test script'!$H$2:$H$133,"Fail") -> 0 | F15: =COUNTIFS('Test script'!$B$2:$B$133,$B15,'Test script'!$H$2:$H$133,"Blocked") -> 0 | G15: =COUNTIFS('Test script'!$B$2:$B$133,$B15,'Test script'!$H$2:$H$133,"Not run") -> 10 | H15: =C15-G15 -> 0 | I15: =IF(H15=0,"-",D15/H15) -> -
B16: S9 Sales | C16: =COUNTIF('Test script'!$B$2:$B$133,B16) -> 15 | D16: =COUNTIFS('Test script'!$B$2:$B$133,$B16,'Test script'!$H$2:$H$133,"Pass") -> 0 | E16: =COUNTIFS('Test script'!$B$2:$B$133,$B16,'Test script'!$H$2:$H$133,"Fail") -> 0 | F16: =COUNTIFS('Test script'!$B$2:$B$133,$B16,'Test script'!$H$2:$H$133,"Blocked") -> 0 | G16: =COUNTIFS('Test script'!$B$2:$B$133,$B16,'Test script'!$H$2:$H$133,"Not run") -> 15 | H16: =C16-G16 -> 0 | I16: =IF(H16=0,"-",D16/H16) -> -
B17: S10 Marketplace | C17: =COUNTIF('Test script'!$B$2:$B$133,B17) -> 13 | D17: =COUNTIFS('Test script'!$B$2:$B$133,$B17,'Test script'!$H$2:$H$133,"Pass") -> 0 | E17: =COUNTIFS('Test script'!$B$2:$B$133,$B17,'Test script'!$H$2:$H$133,"Fail") -> 0 | F17: =COUNTIFS('Test script'!$B$2:$B$133,$B17,'Test script'!$H$2:$H$133,"Blocked") -> 0 | G17: =COUNTIFS('Test script'!$B$2:$B$133,$B17,'Test script'!$H$2:$H$133,"Not run") -> 13 | H17: =C17-G17 -> 0 | I17: =IF(H17=0,"-",D17/H17) -> -
B18: X Cross-cutting | C18: =COUNTIF('Test script'!$B$2:$B$133,B18) -> 4 | D18: =COUNTIFS('Test script'!$B$2:$B$133,$B18,'Test script'!$H$2:$H$133,"Pass") -> 0 | E18: =COUNTIFS('Test script'!$B$2:$B$133,$B18,'Test script'!$H$2:$H$133,"Fail") -> 0 | F18: =COUNTIFS('Test script'!$B$2:$B$133,$B18,'Test script'!$H$2:$H$133,"Blocked") -> 0 | G18: =COUNTIFS('Test script'!$B$2:$B$133,$B18,'Test script'!$H$2:$H$133,"Not run") -> 4 | H18: =C18-G18 -> 0 | I18: =IF(H18=0,"-",D18/H18) -> -
B19: Total | C19: =SUM(C6:C18) -> 132 | D19: =SUM(D6:D18) -> 0 | E19: =SUM(E6:E18) -> 0 | F19: =SUM(F6:F18) -> 0 | G19: =SUM(G6:G18) -> 132 | H19: =SUM(H6:H18) -> 0 | I19: =IF(H19=0,"-",D19/H19) -> -
B21: Open defects | C21: =COUNTIF(Defects!$G$3:$G$500,"Open") -> 0

Sheet Test script
A1: ID | B1: Sprint | C1: Area | D1: Sign in as | E1: Steps | F1: Test data | G1: Expected result | H1: Status | I1: Actual result / notes | J1: Tester | K1: Date
A2: F-01 | B2: S0 Foundation | C2: Public site | D2: Signed out | E2: Open the home page. Click Features, Pricing, About, Contact and Find a property. | F2: - | G2: Hero reads 'Rentals and plot sales, without the paperwork'. Every page loads in the navy/amber design. Pricing shows the 4 plans from the database. | H2: Not run
A3: F-02 | B3: S0 Foundation | C3: Sign in | D3: Signed out | E3: Open Sign in. Click a demo account email in the demo panel. | F3: - | G3: The email fills in. Demo password and a link to the dev mailbox are shown (Development only). Show/hide password works. | H3: Not run
A4: F-03 | B4: S0 Foundation | C4: Register | D4: Signed out | E4: Click Create an account. Enter full name, email, password, tick the terms. Submit. | F4: Name: QA Tester; your own email (or qa1@smartbiz.test); password Qa@123456 | G4: 'Check your email' page. A confirmation email arrives (dev mailbox if SMTP isn't set). | H4: Not run
A5: F-04 | B5: S0 Foundation | C5: Register | D5: Signed out | E5: Try to sign in with the new account before confirming. | F5: Account from F-03 | G5: Sign-in refused with a message to confirm the email, and a link to resend it. | H5: Not run
A6: F-05 | B6: S0 Foundation | C6: Register | D6: New account | E6: Click the confirmation link in the email, then sign in. | F6: - | G6: Email confirmed. After sign-in you land on 'Create business' (no business yet). | H6: Not run
A7: F-06 | B7: S0 Foundation | C7: Create business | D7: New account | E7: Create a business of type Owner. | F7: Name: QA Estates; type Owner | G7: Dashboard opens for QA Estates. Subscription shows a 14-day trial. Credits page shows the trial plan's credits with an 'Allocation' history line. | H7: Not run
A8: F-07 | B8: S0 Foundation | C8: Tenant isolation | D8: owner@ | E8: Open Properties in Acacia Gardens. Switch business to Savanna Homes and open Properties again. | F8: - | G8: Acacia shows Acacia Court and Acacia Shopping Centre only. Savanna shows Savanna Heights only. No data from the other business appears anywhere. | H8: Not run
A9: F-08 | B9: S0 Foundation | C9: Tenant isolation | D9: owner@ | E9: In Acacia Gardens open any invoice and copy its URL. Switch to Savanna Homes and paste the URL. | F9: - | G9: Not found (404). A record from another business can't be opened by URL. | H9: Not run
A10: F-09 | B10: S0 Foundation | C10: Roles | D10: viewer@ | E10: Browse Tenants, Leases, Invoices. Then type /Tenants/Create in the address bar. | F10: - | G10: Lists are readable; no Add/Edit/Record buttons. The create page is refused (access denied). | H10: Not run
A11: F-10 | B11: S0 Foundation | C11: Roles | D11: staff@ | E11: Create a tenant. Then try to open Subscription > Renew, Business settings and Team. | F11: - | G11: Tenant is created. Renew, Business settings and Team are not available to a User. | H11: Not run
A12: F-11 | B12: S0 Foundation | C12: Business switcher | D12: owner@ | E12: Use the switcher at the top of the sidebar to change business. | F12: - | G12: Both businesses listed with their type and role (Owner). Switching changes the business name and data immediately. | H12: Not run
A13: SUB-01 | B13: S1 Subscriptions | C13: Suspended access | D13: lapsed@ | E13: Sign in and try to open Properties. | F13: - | G13: Redirected to the Subscription page: status Suspended, with the payment awaiting approval shown. Other pages aren't reachable. | H13: Not run
... A133: X-04 | B133: X Cross-cutting | C133: Sign out | D133: Any | E133: Sign out, then press Back. | F133: - | G133: You're signed out; protected pages ask you to sign in. | H133: Not run

Sheet Defects
A1: Defect ID | B1: Test ID | C1: Severity | D1: What happened | E1: Steps to reproduce | F1: Expected | G1: Status | H1: Fixed in (zip / date)
A2: EXAMPLE | B2: SA-05 | C2: High | D2: Recording 400,000 showed an error page instead of the receipt. | E2: Savanna Homes > Sales > SL-00006 > Record payment 400,000 M-PESA SVQ1W2E3R4 | F2: Payment recorded; deposit shown as paid | G2: Open
