Workbook

Sheet Read me
B2: SmartBiz Estate: property development and sale walkthrough
B3: A real project from start to finish: buy land, budget and record costs, subdivide, price, sell five plots in different ways, advertise, and check the margins at every step.
B5: The story
B6: Business | C6: Tujenge Land Developers (Developer), created by owner@smartbiz.test (password Demo@12345).
B7: Project | C7: Kitengela Gardens Phase 1: 2 acres on Namanga Road, Kitengela, bought for KES 9,000,000 (budgeted 9,500,000), subdivided into 16 plots of 450 sqm: Plots 1-12 at 1,200,000 and Plots 13-16 at 1,500,000.
B8: Buyers | C8: Mercy pays cash and gets her title. Peter pays by instalments and falls behind. Baraka Investments Ltd pays quarterly. Grace reserves and withdraws. John's cheque bounces. A lead from the website reserves Plot 5 to test auto-hiding.
B10: Before you start
B11: Environment | C11: Any database (demo data can stay). Everything happens in a NEW business, so nothing else interferes. Use Development (emails in /dev/mailbox) or real SMTP with an inbox you can open.
B12: Dates | C12: T = the day you run the test. T-100 = 100 days before. 'Sale date + 1 month' = the same day next month. Back-dated entries are allowed; future-dated actual costs and sales are not.
B13: Order | C13: Run top to bottom. Each phase builds on the one before; the figures in the checkpoints assume every earlier step passed.
B14: Credits | C14: Note the starting balance (B0) in step A-02. Only the lead (10) and PDFs (2 each) use credits in this script.
B16: How to record results
B17: Cells you fill in | C17: Only the shaded columns on 'Test script': Status, Actual result / notes, Tester, Date.
B18: Status | C18: Not run, Pass, Fail or Blocked (couldn't run because an earlier step failed).
B19: Fail | C19: Write what you saw in 'Actual result / notes' and log it on 'Defects' with the step ID.
B20: Scenario | C20: The 'Scenario' sheet has every budget line, cost, plot and sale plan in one place, plus the key expected figures.

Sheet Summary
B2: Results by phase
B3: Updates automatically from the Status column on 'Test script'. Pass rate = Pass / (steps run).
B5: Phase | C5: Steps | D5: Pass | E5: Fail | F5: Blocked | G5: Not run | H5: Run | I5: Pass rate
B6: A Set up the business | C6: =COUNTIF('Test script'!$B$2:$B$71,B6) -> 3 | D6: =COUNTIFS('Test script'!$B$2:$B$71,$B6,'Test script'!$G$2:$G$71,"Pass") -> 0 | E6: =COUNTIFS('Test script'!$B$2:$B$71,$B6,'Test script'!$G$2:$G$71,"Fail") -> 0 | F6: =COUNTIFS('Test script'!$B$2:$B$71,$B6,'Test script'!$G$2:$G$71,"Blocked") -> 0 | G6: =COUNTIFS('Test script'!$B$2:$B$71,$B6,'Test script'!$G$2:$G$71,"Not run") -> 3 | H6: =C6-G6 -> 0 | I6: =IF(H6=0,"-",D6/H6) -> -
B7: B Land purchase and budget | C7: =COUNTIF('Test script'!$B$2:$B$71,B7) -> 5 | D7: =COUNTIFS('Test script'!$B$2:$B$71,$B7,'Test script'!$G$2:$G$71,"Pass") -> 0 | E7: =COUNTIFS('Test script'!$B$2:$B$71,$B7,'Test script'!$G$2:$G$71,"Fail") -> 0 | F7: =COUNTIFS('Test script'!$B$2:$B$71,$B7,'Test script'!$G$2:$G$71,"Blocked") -> 0 | G7: =COUNTIFS('Test script'!$B$2:$B$71,$B7,'Test script'!$G$2:$G$71,"Not run") -> 5 | H7: =C7-G7 -> 0 | I7: =IF(H7=0,"-",D7/H7) -> -
B8: C Actual costs | C8: =COUNTIF('Test script'!$B$2:$B$71,B8) -> 6 | D8: =COUNTIFS('Test script'!$B$2:$B$71,$B8,'Test script'!$G$2:$G$71,"Pass") -> 0 | E8: =COUNTIFS('Test script'!$B$2:$B$71,$B8,'Test script'!$G$2:$G$71,"Fail") -> 0 | F8: =COUNTIFS('Test script'!$B$2:$B$71,$B8,'Test script'!$G$2:$G$71,"Blocked") -> 0 | G8: =COUNTIFS('Test script'!$B$2:$B$71,$B8,'Test script'!$G$2:$G$71,"Not run") -> 6 | H8: =C8-G8 -> 0 | I8: =IF(H8=0,"-",D8/H8) -> -
B9: D Subdivision and plots | C9: =COUNTIF('Test script'!$B$2:$B$71,B9) -> 6 | D9: =COUNTIFS('Test script'!$B$2:$B$71,$B9,'Test script'!$G$2:$G$71,"Pass") -> 0 | E9: =COUNTIFS('Test script'!$B$2:$B$71,$B9,'Test script'!$G$2:$G$71,"Fail") -> 0 | F9: =COUNTIFS('Test script'!$B$2:$B$71,$B9,'Test script'!$G$2:$G$71,"Blocked") -> 0 | G9: =COUNTIFS('Test script'!$B$2:$B$71,$B9,'Test script'!$G$2:$G$71,"Not run") -> 6 | H9: =C9-G9 -> 0 | I9: =IF(H9=0,"-",D9/H9) -> -
B10: E Margins before selling | C10: =COUNTIF('Test script'!$B$2:$B$71,B10) -> 6 | D10: =COUNTIFS('Test script'!$B$2:$B$71,$B10,'Test script'!$G$2:$G$71,"Pass") -> 0 | E10: =COUNTIFS('Test script'!$B$2:$B$71,$B10,'Test script'!$G$2:$G$71,"Fail") -> 0 | F10: =COUNTIFS('Test script'!$B$2:$B$71,$B10,'Test script'!$G$2:$G$71,"Blocked") -> 0 | G10: =COUNTIFS('Test script'!$B$2:$B$71,$B10,'Test script'!$G$2:$G$71,"Not run") -> 6 | H10: =C10-G10 -> 0 | I10: =IF(H10=0,"-",D10/H10) -> -
B11: F Sale 1: cash in full (Mercy) | C11: =COUNTIF('Test script'!$B$2:$B$71,B11) -> 6 | D11: =COUNTIFS('Test script'!$B$2:$B$71,$B11,'Test script'!$G$2:$G$71,"Pass") -> 0 | E11: =COUNTIFS('Test script'!$B$2:$B$71,$B11,'Test script'!$G$2:$G$71,"Fail") -> 0 | F11: =COUNTIFS('Test script'!$B$2:$B$71,$B11,'Test script'!$G$2:$G$71,"Blocked") -> 0 | G11: =COUNTIFS('Test script'!$B$2:$B$71,$B11,'Test script'!$G$2:$G$71,"Not run") -> 6 | H11: =C11-G11 -> 0 | I11: =IF(H11=0,"-",D11/H11) -> -
B12: G Sale 2: instalments with arrears (Peter) | C12: =COUNTIF('Test script'!$B$2:$B$71,B12) -> 6 | D12: =COUNTIFS('Test script'!$B$2:$B$71,$B12,'Test script'!$G$2:$G$71,"Pass") -> 0 | E12: =COUNTIFS('Test script'!$B$2:$B$71,$B12,'Test script'!$G$2:$G$71,"Fail") -> 0 | F12: =COUNTIFS('Test script'!$B$2:$B$71,$B12,'Test script'!$G$2:$G$71,"Blocked") -> 0 | G12: =COUNTIFS('Test script'!$B$2:$B$71,$B12,'Test script'!$G$2:$G$71,"Not run") -> 6 | H12: =C12-G12 -> 0 | I12: =IF(H12=0,"-",D12/H12) -> -
B13: H Sale 3: company, quarterly (Baraka Ltd) | C13: =COUNTIF('Test script'!$B$2:$B$71,B13) -> 3 | D13: =COUNTIFS('Test script'!$B$2:$B$71,$B13,'Test script'!$G$2:$G$71,"Pass") -> 0 | E13: =COUNTIFS('Test script'!$B$2:$B$71,$B13,'Test script'!$G$2:$G$71,"Fail") -> 0 | F13: =COUNTIFS('Test script'!$B$2:$B$71,$B13,'Test script'!$G$2:$G$71,"Blocked") -> 0 | G13: =COUNTIFS('Test script'!$B$2:$B$71,$B13,'Test script'!$G$2:$G$71,"Not run") -> 3 | H13: =C13-G13 -> 0 | I13: =IF(H13=0,"-",D13/H13) -> -
B14: I Cancelling and reversing (Grace, John) | C14: =COUNTIF('Test script'!$B$2:$B$71,B14) -> 5 | D14: =COUNTIFS('Test script'!$B$2:$B$71,$B14,'Test script'!$G$2:$G$71,"Pass") -> 0 | E14: =COUNTIFS('Test script'!$B$2:$B$71,$B14,'Test script'!$G$2:$G$71,"Fail") -> 0 | F14: =COUNTIFS('Test script'!$B$2:$B$71,$B14,'Test script'!$G$2:$G$71,"Blocked") -> 0 | G14: =COUNTIFS('Test script'!$B$2:$B$71,$B14,'Test script'!$G$2:$G$71,"Not run") -> 5 | H14: =C14-G14 -> 0 | I14: =IF(H14=0,"-",D14/H14) -> -
B15: J Margins after selling | C15: =COUNTIF('Test script'!$B$2:$B$71,B15) -> 4 | D15: =COUNTIFS('Test script'!$B$2:$B$71,$B15,'Test script'!$G$2:$G$71,"Pass") -> 0 | E15: =COUNTIFS('Test script'!$B$2:$B$71,$B15,'Test script'!$G$2:$G$71,"Fail") -> 0 | F15: =COUNTIFS('Test script'!$B$2:$B$71,$B15,'Test script'!$G$2:$G$71,"Blocked") -> 0 | G15: =COUNTIFS('Test script'!$B$2:$B$71,$B15,'Test script'!$G$2:$G$71,"Not run") -> 4 | H15: =C15-G15 -> 0 | I15: =IF(H15=0,"-",D15/H15) -> -
B16: K Listing, lead and auto-hide | C16: =COUNTIF('Test script'!$B$2:$B$71,B16) -> 7 | D16: =COUNTIFS('Test script'!$B$2:$B$71,$B16,'Test script'!$G$2:$G$71,"Pass") -> 0 | E16: =COUNTIFS('Test script'!$B$2:$B$71,$B16,'Test script'!$G$2:$G$71,"Fail") -> 0 | F16: =COUNTIFS('Test script'!$B$2:$B$71,$B16,'Test script'!$G$2:$G$71,"Blocked") -> 0 | G16: =COUNTIFS('Test script'!$B$2:$B$71,$B16,'Test script'!$G$2:$G$71,"Not run") -> 7 | H16: =C16-G16 -> 0 | I16: =IF(H16=0,"-",D16/H16) -> -
B17: L Reports and statements | C17: =COUNTIF('Test script'!$B$2:$B$71,B17) -> 4 | D17: =COUNTIFS('Test script'!$B$2:$B$71,$B17,'Test script'!$G$2:$G$71,"Pass") -> 0 | E17: =COUNTIFS('Test script'!$B$2:$B$71,$B17,'Test script'!$G$2:$G$71,"Fail") -> 0 | F17: =COUNTIFS('Test script'!$B$2:$B$71,$B17,'Test script'!$G$2:$G$71,"Blocked") -> 0 | G17: =COUNTIFS('Test script'!$B$2:$B$71,$B17,'Test script'!$G$2:$G$71,"Not run") -> 4 | H17: =C17-G17 -> 0 | I17: =IF(H17=0,"-",D17/H17) -> -
B18: M Things that must be refused | C18: =COUNTIF('Test script'!$B$2:$B$71,B18) -> 9 | D18: =COUNTIFS('Test script'!$B$2:$B$71,$B18,'Test script'!$G$2:$G$71,"Pass") -> 0 | E18: =COUNTIFS('Test script'!$B$2:$B$71,$B18,'Test script'!$G$2:$G$71,"Fail") -> 0 | F18: =COUNTIFS('Test script'!$B$2:$B$71,$B18,'Test script'!$G$2:$G$71,"Blocked") -> 0 | G18: =COUNTIFS('Test script'!$B$2:$B$71,$B18,'Test script'!$G$2:$G$71,"Not run") -> 9 | H18: =C18-G18 -> 0 | I18: =IF(H18=0,"-",D18/H18) -> -
B19: Total | C19: =SUM(C6:C18) -> 70 | D19: =SUM(D6:D18) -> 0 | E19: =SUM(E6:E18) -> 0 | F19: =SUM(F6:F18) -> 0 | G19: =SUM(G6:G18) -> 70 | H19: =SUM(H6:H18) -> 0 | I19: =IF(H19=0,"-",D19/H19) -> -
B21: Open defects | C21: =COUNTIF(Defects!$G$3:$G$500,"Open") -> 0

Sheet Scenario
B2: Budget (step B-03) and actual costs (C-01 to C-05, E-06)
B3: Category | C3: Budget | D3: Actual | E3: Expected | F3: Actual lines
B4: Land purchase price | C4: 9500000 | D4: 9000000 | E4: =D4 -> 9000000 | F4: Purchase price (B-05)
B5: Purchase costs | C5: 500000 | D5: 460000 | E5: =MAX(C5,D5) -> 500000 | F5: Stamp duty 360,000; conveyancing 100,000
B6: Approvals | C6: 200000 | D6: 200000 | E6: =MAX(C6,D6) -> 200000 | F6: County approval and LCB consent
B7: Subdivision | C7: 600000 | D7: 650000 | E7: =MAX(C7,D7) -> 650000 | F7: Survey 450,000; beacons 80,000; titles 120,000
B8: Infrastructure | C8: 2400000 | D8: 1300000 | E8: =MAX(C8,D8) -> 2400000 | F8: Murram roads (power and water still to come)
B9: Marketing | C9: 300000 | D9: 0 | E9: =MAX(C9,D9) -> 300000 | F9: None yet
B10: Total (before plot fencing) | C10: =SUM(C4:C9) -> 13500000 | D10: =SUM(D4:D9) -> 11610000 | E10: =SUM(E4:E9) -> 13050000
B11: Plot 16 fencing (E-06, Plot 16 only) | D11: 60000 | E11: 60000
B13: Plots (D-02, D-03)
B14: Plots | C14: Count | D14: Size (sqm) | E14: Price each | F14: Total
B15: Plot 1 to Plot 12 | C15: 12 | D15: 450 | E15: 1200000 | F15: =C15*E15 -> 14400000
B16: Plot 13 to Plot 16 | C16: 4 | D16: 450 | E16: 1500000 | F16: =C16*E16 -> 6000000
B18: Key expected figures
B19: Figure | C19: Value | F19: Where checked
B20: Expected cost per plot (by size) | C20: =E10/16 -> 815625 | F20: E-01
B21: Projected sales revenue | C21: =SUM(F15:F16) -> 20400000 | F21: E-03
B22: Projected margin (before fencing) | C22: =C21-E10 -> 7350000 | F22: E-03: 36%
B23: Expected total with fencing | C23: =E10+E11 -> 13110000 | F23: E-06
B24: Projected margin with fencing | C24: =C21-C23 -> 7290000 | F24: E-06, J-02: 35.7%
B25: Collected after the sales | C25: 2060000 | F25: J-01, J-02
B26: Break-even after the sales | C26: 8 more units | F26: J-02
B28: Sales (phases F to K)
B29: Sale | C29: Plot | D29: Price | E29: Plan | F29: Payments recorded
B30: SL-00001 Mercy Chebet | C30: Plot 1 | D30: 1200000 | E30: Full payment, sale date T | F30: 1,200,000 bank, ref FT26KT0001; completed
B31: SL-00002 Peter Otieno | C31: Plot 2 | D31: 1200000 | E31: Deposit 240,000 + 6 x 160,000 monthly; sale date T-100 | F31: 240,000 + 160,000 + 160,000 M-PESA; instalment 3 overdue
B32: SL-00003 Baraka Investments Ltd | C32: Plot 13 | D32: 1500000 | E32: Deposit 300,000 + 4 x 300,000 quarterly; sale date T | F32: 300,000 bank, ref FT26KT0002
B33: SL-00004 Grace Wanjiku | C33: Plot 3 | D33: 1200000 | E33: Deposit 240,000 + 12 monthly | F33: None; cancelled
B34: SL-00005 John Kamau | C34: Plot 4 | D34: 1200000 | E34: Deposit 240,000 + 6 monthly | F34: 240,000 cheque, reversed; cancelled
B35: SL-00006 Lead Tester | C35: Plot 5 | D35: 1200000 | E35: Full payment (auto-hide test) | F35: None; cancelled

Sheet Test script
A1: ID | B1: Phase | C1: Area | D1: Steps | E1: Test data | F1: Expected result | G1: Status | H1: Actual result / notes | I1: Tester | J1: Date
A2: A-01 | B2: A Set up the business | C2: New business | D2: Sign in as owner@smartbiz.test. Switcher > Create another business. | E2: Name: Tujenge Land Developers; type Developer; phone 0722 100 200; KRA PIN P051234567X | F2: Dashboard opens for Tujenge Land Developers. Sidebar shows Sales and Costs and margins. | G2: Not run
A3: A-02 | B3: A Set up the business | C3: Starting point | D3: Open Account > Credits. Note the balance as B0. Open Account > Subscription. | E3: - | F3: Trial, 14 days. Credits history shows the trial allocation. Write B0 in the notes; later steps refer to it. | G3: Not run
A4: A-03 | B4: A Set up the business | C4: Business details | D4: Account > Business settings: add email and address. Upload a logo. | E4: Email info@tujenge.test; address Kitengela town | F4: Saved; logo shows (it will appear on PDFs). | G4: Not run
A5: B-01 | B5: B Land purchase and budget | C5: Project | D5: Portfolio > Properties > Add property. | E5: Name: Kitengela Gardens Phase 1; type Land; location Namanga Road, Kitengela; county Kajiado | F5: Property created. | G5: Not run
A6: B-02 | B6: B Land purchase and budget | C6: Budgeted land price | D6: Costs and margins > Kitengela Gardens Phase 1 > Purchase and subdivision. Enter the budget only (not the purchase yet). Save. | E6: Budgeted land price 9,500,000; title KAJIADO/KITENGELA/9001; land size 2 acres; spread shared costs: By size | F6: Saved. Margins tab: 'Land purchase price' budget 9,500,000, actual 0, expected 9,500,000. | G6: Not run
A7: B-03 | B7: B Land purchase and budget | C7: Budget lines | D7: Budget and costs: add five lines, each as Budget estimate, Whole project. | E7: Purchase costs 'Stamp duty, legal, valuation' 500,000 | Subdivision 'Survey, mutation, beacons, titles' 600,000 | Infrastructure 'Roads, water and power' 2,400,000 | Approvals 'County approval and LCB' 200,000 | Marketing 'Signboards and adverts' 300,000 | F7: Five budget lines listed, each tagged Budget. | G7: Not run
A8: B-04 | B8: B Land purchase and budget | C8: Checkpoint: budget only | D8: Open Margins. | E8: - | F8: Budget 13,500,000; spent 0; expected total 13,500,000. Each category shows 'x left'. No sales box yet (no plots). | G8: Not run
A9: B-05 | B9: B Land purchase and budget | C9: Buy the land | D9: Purchase and subdivision: enter the purchase. Save. | E9: Purchase price 9,000,000; date T-120; bought from 'Ole Nkoile family' | F9: Saved. Margins: land row budget 9,500,000, actual 9,000,000, expected 9,000,000. Expected total 13,000,000; spent 9,000,000. | G9: Not run
A10: C-01 | B10: C Actual costs | C10: Purchase costs | D10: Budget and costs > Actual cost, Purchase costs. Add two lines. | E10: Stamp duty (4%) 360,000, date T-118, supplier KRA | Conveyancing 100,000, date T-118, supplier Mwangi & Co Advocates | F10: Two actual lines. Purchase costs: actual 460,000 vs budget 500,000 ('40,000 left'). | G10: Not run
A11: C-02 | B11: C Actual costs | C11: Receipt | D11: Edit the stamp duty line and attach a receipt (PDF or JPG). Open it from the list. | E11: Any small PDF | F11: Paperclip 'Receipt' link opens the file. | G11: Not run
A12: C-03 | B12: C Actual costs | C12: Approvals | D12: Add an actual Approvals cost. | E12: County approval and LCB consent 200,000, date T-110 | F12: Approvals: actual 200,000 = budget ('on budget'). | G12: Not run
A13: C-04 | B13: C Actual costs | C13: Subdivision costs | D13: Add three actual Subdivision costs. | E13: Survey and mutation 450,000 (T-100) | Beacons 80,000 (T-95) | Title processing, 16 titles 120,000 (T-60) | F13: Subdivision: actual 650,000 vs budget 600,000 shown as '+50,000 over' in red. | G13: Not run
... A71: M-09 | B71: M Things that must be refused | C71: Delete a sold plot | D71: Try to delete Plot 1. | E71: - | F71: Refused: it has sale history (mark it inactive instead). | G71: Not run

Sheet Defects
A1: Defect ID | B1: Test ID | C1: Severity | D1: What happened | E1: Steps to reproduce | F1: Expected | G1: Status | H1: Fixed in (zip / date)
A2: EXAMPLE | B2: G-05 | C2: High | D2: Peter's paid figure showed 400,000 instead of 560,000. | E2: Tujenge > Sales > SL-00002 after recording the three payments in G-03 and G-04 | F2: Paid 560,000 (47%); balance 640,000; overdue 160,000 | G2: Open
